nonebot_plugin_leetcodeAPI_KHASA/__init__.py
nonebot_plugin_leetcodeAPI_KHASA/config.py
nonebot_plugin_leetcodeAPI_KHASA/get_discussion_data.py
nonebot_plugin_leetcodeAPI_KHASA/get_problem_data.py
nonebot_plugin_leetcodeAPI_KHASA/get_user_data.py
nonebot_plugin_leetcodeAPI_KHASA/templates/detailed_user_profile_template.html
nonebot_plugin_leetcodeAPI_KHASA/templates/discussion_by_id_template.html
nonebot_plugin_leetcodeAPI_KHASA/templates/discussion_comments_template.html
nonebot_plugin_leetcodeAPI_KHASA/templates/discussion_template.html
nonebot_plugin_leetcodeAPI_KHASA/templates/many_problems_template.html
nonebot_plugin_leetcodeAPI_KHASA/templates/problem_template.html
nonebot_plugin_leetcodeAPI_KHASA/templates/user_badges_template.html
nonebot_plugin_leetcodeAPI_KHASA/templates/user_contest_history_template.html
nonebot_plugin_leetcodeAPI_KHASA/templates/user_profile_template.html
nonebot_plugin_leetcodeAPI_KHASA/templates/user_solved_problems_template.html
nonebot_plugin_leetcodeAPI_KHASA/templates/user_submissions_template.html
nonebot_plugin_leetcodeAPI_KHASA-0.3.7.dist-info/LICENSE
nonebot_plugin_leetcodeAPI_KHASA-0.3.7.dist-info/METADATA
nonebot_plugin_leetcodeAPI_KHASA-0.3.7.dist-info/WHEEL
nonebot_plugin_leetcodeAPI_KHASA-0.3.7.dist-info/top_level.txt
nonebot_plugin_leetcodeAPI_KHASA-0.3.7.dist-info/RECORD
