Metadata-Version: 2.1
Name: nonebot_plugin_leetcodeAPI_KHASA
Version: 0.3.7
Summary: A Nonebot plugin for interacting with LeetCode (Using API made by alfaarghya)
Home-page: https://github.com/KhasAlushird/nonebot_plugin_leetcodeAPI_KHASA
Author: KhasAlushird
Author-email: KhasAlushird@sjtu.edu.cn
Classifier: Programming Language :: Python :: 3
Classifier: License :: OSI Approved :: MIT License
Classifier: Operating System :: OS Independent
Requires-Python: >=3.6
License-File: LICENSE
Requires-Dist: nonebot2>=2.2.0
Requires-Dist: nonebot-adapter-onebot>=2.2.0
Requires-Dist: nonebot-plugin-htmlrender>=0.1.0
Requires-Dist: httpx>=0.21.0
Requires-Dist: jinja2>=3.0.0
Requires-Dist: nonebot-plugin-localstore>=0.1.0
